micronus/__init__.py
micronus/__main__.py
micronus/data_pipeline.py
micronus/decoder.py
micronus/dotproduct_attention.py
micronus/encoder.py
micronus/inference.py
micronus/multihead_attention.py
micronus/plot_load.py
micronus/positional_encoding.py
micronus/train.py
micronus/transformer_model.py
micronus-0.0.4.dist-info/LICENSE.txt
micronus-0.0.4.dist-info/METADATA
micronus-0.0.4.dist-info/WHEEL
micronus-0.0.4.dist-info/top_level.txt
micronus-0.0.4.dist-info/RECORD
