Metadata-Version: 2.1
Name: micronus
Version: 0.0.4
Summary: A light weight transformer model
Home-page: UNKNOWN
Author: Chamath Attanyaka
License: MIT
Platform: UNKNOWN
Requires-Python: >=3.8
Requires-Dist: keras (==2.4.3)
Requires-Dist: matplotlib (>=3.3.2)
Requires-Dist: numpy (==1.19.3)
Requires-Dist: tensorflow (==2.4.1)
